djangocms_contact
